{
	"QMainWindow":[
		{
			"tittle":"Test flow ",
			"icon":"::/Images/Images/Assa_Abloy.png",
			"frameless": true,
			"transluscentBg": true,
			"sizeGrip": "sizeGrip",
			"navigation":[
				{
					"minimize":"minimizeBtn",
					"close": "closeBtn",
					"restore":[
						{	
							"buttonName": "restoreBtn",
							"normalIcon": ":/Icons/Images/icons/square.svg",
							"maximizedIcon": ":/Icons/Images/icons/copy.svg"
						}
					],
					"moveWindow": "headerContiner",
					"tittleBar": "headerContiner"
				}
			]
		}
	],
	"QCustomSlideMenu": [
		{
		"name": "leftMenuContainer",
		"defaultSize": [{
			"width": 340,
			"height": "parent"
		}],
		"collapsedSize": [{
			"width": 110,
			"height": "parent"
		}],
		"expandedSize": [{
			"width": 340	,

			"height": "parent"
		}],

		"toggleButton": [{
			"buttonName": "menuBtn",
			"icons": [{
				"whenMenuIsCollapsed": ":/Icons/Images/icons/align-justify.svg",
				"whenMenuIsExpanded": ":/Icons/Images/icons/chevron-left.svg"
			}]
		}],

		"menuTransitionAnimation": [{
			"animationDuration": 500,
			"animationEasingCurve": "Linear"
			}]
		},
		{
		"name": "centerMenuContainer",
		"defaultSize": [{
			"width": 0,
			"height": "parent"
		}],
		"collapsedSize": [{
			"width": 0,
			"height": "parent"
		}],
		"expandedSize": [{
			"width": 90,
			"height": "parent"
		}],
		"menuTransitionAnimation": [{
			"animationDuration": 500,
			"animationEasingCurve": "Linear"
			}]
		},
		{
		"name": "rightMenuContainer",
		"defaultSize": [{
			"width": 0,
			"height": "auto"
		}],
		"collapsedSize": [{
			"width": 0,
			"height": "auto"
		}],
		"expandedSize": [{
			"width": 300,
			"height": "auto"
		}],
		"menuTransitionAnimation": [{
			"animationDuration": 500,
			"animationEasingCurve": "Linear"
			}]
		}
	],

	"QStackedWidget":[

		{
			"name":"centerMenuPages",
			"navigation":[
				{
					"navigationButtons":[
						{
							"Btemperature": "page",
							"Bhumidity": "page_2",
							"Bflow": "page_3",
							"Bpressure": "page_6",
							"Btempcam": "page_7",
							"Bsolar": "page_8"


						}
					]
				}
			]

		},

		{
			"name":"mainPages",
			"navigation":[
				{
					"navigationButtons":[
						{
							"Btemperature": "m1",
							"Bhumidity": "m2",
							"Bflow": "page_3",
							"Bpressure": "page_6",
							"Btempcam": "page_7",
							"Bsolar": "page_8"


						}
					]
				}
			]

		},

		{
			"name":"mainPages_2",
			"navigation":[
				{
					"navigationButtons":[
						{
							"t1": "m1_2",
							"t2": "m2_2"


						}
					]
				}
			]

		}
	],
	"QPushButtonGroup": [

		{
			"Buttons": [
				"Btemperature",
				"Bhumidity",
				"Bflow"
			],
			"Style":[{
				"Active": "background-color: #2c313c;",
				"NotActive": ""
			}]
		},
		{
			"Buttons": [
				"t1",
				"t2",
				"t3",
				"t4",
				"t5",
				"t6",
				"t7",
				"t8",
				"t9",
				"t10"

			],
			"Style":[{
				"Active": "background-color: #3d4a95;",
				"NotActive": ""
			}]
		}




	]
}